pycorese/__init__.py
pycorese/api.py
pycorese/corese_version.py
pycorese/jpype_bridge.py
pycorese/py4J_bridge.py
pycorese-1.0.1.data/data/share/pycorese/corese-core-4.6.0-jar-with-dependencies.jar
pycorese-1.0.1.data/data/share/pycorese/corese-python-4.6.0-jar-with-dependencies.jar
pycorese-1.0.1.dist-info/LICENSE
pycorese-1.0.1.dist-info/METADATA
pycorese-1.0.1.dist-info/WHEEL
pycorese-1.0.1.dist-info/top_level.txt
pycorese-1.0.1.dist-info/RECORD
