Metadata-Version: 2.1
Name: pycorese
Version: 1.0.1
Summary: corese-python: Corese Python API for Corese SPARQL engine.
Author-email: Anna Bobasheva <anna.bobasheva@inria.fr>, Jean-Luc Szpyrka <jean-luc.szpyrka@inria.fr>, Remi Ceres <remi.ceres@inria.fr>
License: GNU LESSER GENERAL PUBLIC LICENSE
Project-URL: Homepage, https://corese-stack.github.io/corese-python/
Project-URL: Issues, https://github.com/corese-stack/corese-python/issues
Project-URL: Documentation, https://corese-stack.github.io/corese-python/
Project-URL: Repository, https://github.com/corese-stack/corese-python.git
Keywords: Query Engine,SPARQL,SHACL,RDF,RDFS,OWL,Reasoning,Knowledge Graph
Classifier: License :: OSI Approved :: GNU Lesser General Public License v2 (LGPLv2)
Classifier: Intended Audience :: Science/Research
Classifier: Topic :: Scientific/Engineering
Classifier: Programming Language :: Python :: 3
Requires-Python: >=3.10
License-File: LICENSE
Requires-Dist: py4j>=0.10.9.7
Requires-Dist: jpype1>=1.5.0
Requires-Dist: pandas>=1.3.3
